Workbook

Sheet Dashboard
I2: Dashboard de Investimentos em FIIs
I4: ="Perfil "&Calculos!C30&" · simulação de aportes mensais com reinvestimento" -> Perfil Agressivo · simulação de aportes mensais com reinvestimento
I5: ⚙ Editar parâmetros | K5: ▦ Tabelas dinâmicas | M5: ☰ Base de dados
B7: SALÁRIO | D7: APORTE MENSAL | F7: PRAZO | I7: PATRIMÔNIO ACUMULADO | K7: DIVIDENDOS MENSAIS | M7: PERFIL ATIVO
B8: =salario -> 2000 | D8: =aporte -> 200 | F8: =qtde_anos -> 5 | I8: =patrimonio -> 16755.383 | K8: =dividendos -> 100.5323 | M8: =Calculos!C30 -> Agressivo
B9: Base da sugestão de 30% | D9: =Calculos!C13 -> 600 | F9: =taxa_mensal -> 0.01079 | I9: =aporte*12*qtde_anos -> 12000 | K9: =redimento_carteira -> 0.006 | M9: Escolhido na aba Calculos
B11: ALOCAÇÃO SUGERIDA DO APORTE (PERFIL ATIVO) | I11: PATRIMÔNIO ACUMULADO POR HORIZONTE
B28: EVOLUÇÃO ANUAL: TOTAL APORTADO × RENDIMENTO | I28: DIVIDENDOS MENSAIS ESTIMADOS POR HORIZONTE
B45: CENÁRIOS DE ACÚMULO | I45: DISTRIBUIÇÃO DO APORTE POR TIPO DE FII
B46: Horizonte | D46: Patrimônio | F46: Dividendos/mês | I46: Tipo de FII | K46: % sugerido | M46: Valor (R$)
B47: =Calculos!B23 -> Quanto em 2 anos | D47: =Calculos!C23 -> 5445.5255 | F47: =Calculos!D23 -> 32.673153 | I47: =Calculos!B34 -> PAPEL | K47: =Calculos!C34 -> 0.5 | M47: =Calculos!D34 -> 100
B48: =Calculos!B24 -> Quanto em 5 anos | D48: =Calculos!C24 -> 16755.383 | F48: =Calculos!D24 -> 100.5323 | I48: =Calculos!B35 -> TIJOLO | K48: =Calculos!C35 -> 0.1 | M48: =Calculos!D35 -> 20
B49: =Calculos!B25 -> Quanto em 10 anos | D49: =Calculos!C25 -> 48656.843 | F49: =Calculos!D25 -> 291.94106 | I49: =Calculos!B36 -> HIBRIDO | K49: =Calculos!C36 -> 0.05 | M49: =Calculos!D36 -> 10
B50: =Calculos!B26 -> Quanto em 20 anos | D50: =Calculos!C26 -> 225039.68 | F50: =Calculos!D26 -> 1350.2381 | I50: =Calculos!B37 -> FOFs | K50: =Calculos!C37 -> 0.05 | M50: =Calculos!D37 -> 10
B51: =Calculos!B27 -> Quanto em 30 anos | D51: =Calculos!C27 -> 864433.93 | F51: =Calculos!D27 -> 5186.6036 | I51: =Calculos!B38 -> DESENVOLVIMENTO | K51: =Calculos!C38 -> 0.2 | M51: =Calculos!D38 -> 40
B52: ="Prazo escolhido ("&qtde_anos&" anos)" -> Prazo escolhido (5 anos) | D52: =patrimonio -> 16755.383 | F52: =dividendos -> 100.5323 | I52: =Calculos!B39 -> HOTELARIA | K52: =Calculos!C39 -> 0.1 | M52: =Calculos!D39 -> 20
I53: TOTAL | K53: =SUM(K47:K52) -> 1 | M53: =SUM(M47:M52) -> 200
B55: Notas: (1) Projeções com aportes no fim de cada mês e taxa mensal constante, conforme informado em Calculos!C18 (premissa do usuário, não uma previsão de mercado). (2) Dividendos mensais = patrimônio × rendimento da carteira (Calculos!C12). (3) Rentabilidade projetada não garante resultados futuros; este material não constitui recomendação de investimento.

Sheet Calculos
B9: Azul = campo editável · demais células são calculadas automaticamente | D9: Ir ao Dashboard ►
B10: CONFIGURAÇÕES
B11: Salário | C11: 2000
B12: Rendimento Carteira | C12: 0.006
B13: Sugestão Investimento | C13: =C11*30% -> 600
B15: INVESTIMENTO MENSAL | M15: s
B16: Quanto investir por mês? | C16: 200 | XFD16: C16
B17: Por quantos anos? | C17: 5
B18: Taxa de rendimento mensal? | C18: 0.01079
B19: Patrimônio Acumulado? | C19: =FV(taxa_mensal,qtde_anos*12,aporte*-1) -> 16755.383
B20: Dividendos Mensais? | C20: =C19*C12 -> 100.5323
B22: CENÁRIOS | D22: DIVIDENDOS
B23: Quanto em 2 anos | C23: =FV($C$18,2*12,$C$16*-1) -> 5445.5255 | D23: =C23*redimento_carteira -> 32.673153
B24: Quanto em 5 anos | C24: =FV($C$18,5*12,$C$16*-1) -> 16755.383 | D24: =C24*redimento_carteira -> 100.5323
B25: Quanto em 10 anos | C25: =FV($C$18,10*12,$C$16*-1) -> 48656.843 | D25: =C25*redimento_carteira -> 291.94106
B26: Quanto em 20 anos | C26: =FV($C$18,20*12,$C$16*-1) -> 225039.68 | D26: =C26*redimento_carteira -> 1350.2381
B27: Quanto em 30 anos | C27: =FV($C$18,30*12,$C$16*-1) -> 864433.93 | D27: =C27*redimento_carteira -> 5186.6036
B29: ALOCAÇÃO POR PERFIL
B30: PERFIL | C30: Agressivo | D30: ◄ escolha
B31: VALOR A SER INVESTIDO POR MÊS | C31: =C16 -> 200
B33: TIPO DE FII | C33: Percentual Sugerido | D33: Valores
B34: PAPEL | C34: =VLOOKUP($C$30&"-"&B34,Suporte!A4:D22,4,FALSE) -> 0.5 | D34: =$C$31*C34 -> 100
B35: TIJOLO | C35: =VLOOKUP($C$30&"-"&B35,Suporte!A5:D23,4,FALSE) -> 0.1 | D35: =$C$31*C35 -> 20
B36: HIBRIDO | C36: =VLOOKUP($C$30&"-"&B36,Suporte!A6:D24,4,FALSE) -> 0.05 | D36: =$C$31*C36 -> 10
B37: FOFs | C37: =VLOOKUP($C$30&"-"&B37,Suporte!A7:D25,4,FALSE) -> 0.05 | D37: =$C$31*C37 -> 10
B38: DESENVOLVIMENTO | C38: =VLOOKUP($C$30&"-"&B38,Suporte!A8:D26,4,FALSE) -> 0.2 | D38: =$C$31*C38 -> 40
B39: HOTELARIA | C39: =VLOOKUP($C$30&"-"&B39,Suporte!A9:D27,4,FALSE) -> 0.1 | D39: =$C$31*C39 -> 20
B40: TOTAL | C40: =SUM(C34:C39) -> 1 | D40: =SUM(D34:D39) -> 200

Sheet Tabelas_Dinamicas
B2: TABELAS DINÂMICAS · ANÁLISE DE ALOCAÇÃO POR PERFIL | H2: ◄ Dashboard
B3: Fonte: aba Base_Dados (ligada à aba Suporte). As tabelas atualizam ao abrir o arquivo; para forçar, use Dados ▸ Atualizar Tudo.
B5: 1 · Percentual de alocação por perfil e tipo de FII
B6: Cada linha (perfil) soma 100%; compare como cada perfil distribui o aporte.
B8: % do aporte | C8: Tipo de FII
B9: Perfil | C9: PAPEL | D9: TIJOLO | E9: HÍBRIDO | F9: FOFs | G9: DESENVOLVIMENTO | H9: HOTELARIAS
B10: Conservador | C10: 0.3 | D10: 0.5 | E10: 0.1 | F10: 0.1 | G10: 0 | H10: 0
B11: Moderado | C11: 0.32 | D11: 0.35 | E11: 0.08 | F11: 0.05 | G11: 0.1 | H11: 0.1
B12: Agressivo | C12: 0.5 | D12: 0.1 | E12: 0.05 | F12: 0.05 | G12: 0.2 | H12: 0.1
B15: 2 · Valor mensal a investir (R$) por perfil e tipo de FII
B16: Usa o aporte mensal da aba Calculos; recalcula quando o aporte muda e a tabela é atualizada.
B18: Valor a investir (R$) | C18: Tipo de FII
B19: Perfil | C19: PAPEL | D19: TIJOLO | E19: HÍBRIDO | F19: FOFs | G19: DESENVOLVIMENTO | H19: HOTELARIAS
B20: Conservador | C20: 60 | D20: 100 | E20: 20 | F20: 20 | G20: 0 | H20: 0
B21: Moderado | C21: 64 | D21: 70 | E21: 16 | F21: 10 | G21: 20 | H21: 20
B22: Agressivo | C22: 100 | D22: 20 | E22: 10 | F22: 10 | G22: 40 | H22: 20
B25: 3 · Percentual médio por tipo de FII (média dos três perfis)
B26: Mostra onde a carteira, em média, concentra mais recursos.
B28: Tipo de FII | C28: % médio entre perfis | E28: COMO USAR Clique dentro de qualquer tabela dinâmica para abrir o painel de campos (Análise de Tabela Dinâmica). Arraste Perfil e Tipo de FII entre Linhas e Colunas, ou troque o valor analisado entre Percentual e Valor Mensal. Atualize com Dados ▸ Atualizar Tudo.
B29: PAPEL | C29: 0.37333333
B30: TIJOLO | C30: 0.31666667
B31: HÍBRIDO | C31: 0.076666667
B32: FOFs | C32: 0.066666667
B33: DESENVOLVIMENTO | C33: 0.1
B34: HOTELARIAS | C34: 0.066666667

Sheet Suporte
A1: TABELA DE SUPORTE · ALOCAÇÃO POR PERFIL
A2: Percentuais consultados pela função PROCV da aba Calculos. Cada perfil deve somar 100%.
A4: CHAVE | B4: TIPO DE FII | C4: TIPO DE FII | D4: % | F4: CHECAGEM | G4: Soma
A5: Conservador-PAPEL | B5: Conservador | C5: PAPEL | D5: 0.3 | F5: Conservador | G5: =SUMIF($B$5:$B$22,F5,$D$5:$D$22) -> 1
A6: Conservador-TIJOLO | B6: Conservador | C6: TIJOLO | D6: 0.5 | F6: Moderado | G6: =SUMIF($B$5:$B$22,F6,$D$5:$D$22) -> 1
A7: Conservador-HIBRIDO | B7: Conservador | C7: HÍBRIDO | D7: 0.1 | F7: Agressivo | G7: =SUMIF($B$5:$B$22,F7,$D$5:$D$22) -> 1
A8: Conservador-FOFs | B8: Conservador | C8: FOFs | D8: 0.1
A9: Conservador-DESENVOLVIMENTO | B9: Conservador | C9: DESENVOLVIMENTO | D9: 0
A10: Conservador-HOTELARIA | B10: Conservador | C10: HOTELARIAS | D10: 0
A11: Moderado-PAPEL | B11: Moderado | C11: PAPEL | D11: 0.32
A12: Moderado-TIJOLO | B12: Moderado | C12: TIJOLO | D12: 0.35
A13: Moderado-HIBRIDO | B13: Moderado | C13: HÍBRIDO | D13: 0.08
A14: Moderado-FOFs | B14: Moderado | C14: FOFs | D14: 0.05
A15: Moderado-DESENVOLVIMENTO | B15: Moderado | C15: DESENVOLVIMENTO | D15: 0.1
A16: Moderado-HOTELARIA | B16: Moderado | C16: HOTELARIAS | D16: 0.1
A17: Agressivo-PAPEL | B17: Agressivo | C17: PAPEL | D17: 0.5
A18: Agressivo-TIJOLO | B18: Agressivo | C18: TIJOLO | D18: 0.1
A19: Agressivo-HIBRIDO | B19: Agressivo | C19: HÍBRIDO | D19: 0.05
... A22: Agressivo-HOTELARIA | B22: Agressivo | C22: HOTELARIAS | D22: 0.1

Sheet Base_Dados
A1: BASE DE DADOS
A2: Dados ligados por fórmula às abas Suporte e Calculos. Não digite aqui: esta aba alimenta as Tabelas Dinâmicas e o gráfico de evolução do Dashboard.
A4: 1. Alocação por perfil (fonte das tabelas dinâmicas) | F4: 2. Projeção anual de acumulação (fonte do gráfico de evolução)
A5: Perfil | B5: Tipo de FII | C5: Percentual | D5: Valor Mensal (R$) | F5: Ano | G5: Total Aportado (R$) | H5: Patrimônio Acumulado (R$) | I5: Rendimento Acumulado (R$)
A6: =Suporte!B5 -> Conservador | B6: =Suporte!C5 -> PAPEL | C6: =Suporte!D5 -> 0.3 | D6: =C6*aporte -> 60 | F6: 1 | G6: =aporte*12*F6 -> 2400 | H6: =FV(taxa_mensal,F6*12,aporte*-1) -> 2547.6772 | I6: =H6-G6 -> 147.6772
A7: =Suporte!B6 -> Conservador | B7: =Suporte!C6 -> TIJOLO | C7: =Suporte!D6 -> 0.5 | D7: =C7*aporte -> 100 | F7: =F6+1 -> 2 | G7: =aporte*12*F7 -> 4800 | H7: =FV(taxa_mensal,F7*12,aporte*-1) -> 5445.5255 | I7: =H7-G7 -> 645.52546
A8: =Suporte!B7 -> Conservador | B8: =Suporte!C7 -> HÍBRIDO | C8: =Suporte!D7 -> 0.1 | D8: =C8*aporte -> 20 | F8: =F7+1 -> 3 | G8: =aporte*12*F8 -> 7200 | H8: =FV(taxa_mensal,F8*12,aporte*-1) -> 8741.6748 | I8: =H8-G8 -> 1541.6748
A9: =Suporte!B8 -> Conservador | B9: =Suporte!C8 -> FOFs | C9: =Suporte!D8 -> 0.1 | D9: =C9*aporte -> 20 | F9: =F8+1 -> 4 | G9: =aporte*12*F9 -> 9600 | H9: =FV(taxa_mensal,F9*12,aporte*-1) -> 12490.871 | I9: =H9-G9 -> 2890.8706
A10: =Suporte!B9 -> Conservador | B10: =Suporte!C9 -> DESENVOLVIMENTO | C10: =Suporte!D9 -> 0 | D10: =C10*aporte -> 0 | F10: =F9+1 -> 5 | G10: =aporte*12*F10 -> 12000 | H10: =FV(taxa_mensal,F10*12,aporte*-1) -> 16755.383 | I10: =H10-G10 -> 4755.3828
A11: =Suporte!B10 -> Conservador | B11: =Suporte!C10 -> HOTELARIAS | C11: =Suporte!D10 -> 0 | D11: =C11*aporte -> 0 | F11: =F10+1 -> 6 | G11: =aporte*12*F11 -> 14400 | H11: =FV(taxa_mensal,F11*12,aporte*-1) -> 21606.04 | I11: =H11-G11 -> 7206.0402
A12: =Suporte!B11 -> Moderado | B12: =Suporte!C11 -> PAPEL | C12: =Suporte!D11 -> 0.32 | D12: =C12*aporte -> 64 | F12: =F11+1 -> 7 | G12: =aporte*12*F12 -> 16800 | H12: =FV(taxa_mensal,F12*12,aporte*-1) -> 27123.407 | I12: =H12-G12 -> 10323.407
A13: =Suporte!B12 -> Moderado | B13: =Suporte!C12 -> TIJOLO | C13: =Suporte!D12 -> 0.35 | D13: =C13*aporte -> 70 | F13: =F12+1 -> 8 | G13: =aporte*12*F13 -> 19200 | H13: =FV(taxa_mensal,F13*12,aporte*-1) -> 33399.12 | I13: =H13-G13 -> 14199.12
A14: =Suporte!B13 -> Moderado | B14: =Suporte!C13 -> HÍBRIDO | C14: =Suporte!D13 -> 0.08 | D14: =C14*aporte -> 16 | F14: =F13+1 -> 9 | G14: =aporte*12*F14 -> 21600 | H14: =FV(taxa_mensal,F14*12,aporte*-1) -> 40537.412 | I14: =H14-G14 -> 18937.412
A15: =Suporte!B14 -> Moderado | B15: =Suporte!C14 -> FOFs | C15: =Suporte!D14 -> 0.05 | D15: =C15*aporte -> 10 | F15: =F14+1 -> 10 | G15: =aporte*12*F15 -> 24000 | H15: =FV(taxa_mensal,F15*12,aporte*-1) -> 48656.843 | I15: =H15-G15 -> 24656.843
A16: =Suporte!B15 -> Moderado | B16: =Suporte!C15 -> DESENVOLVIMENTO | C16: =Suporte!D15 -> 0.1 | D16: =C16*aporte -> 20 | F16: =F15+1 -> 11 | G16: =aporte*12*F16 -> 26400 | H16: =FV(taxa_mensal,F16*12,aporte*-1) -> 57892.266 | I16: =H16-G16 -> 31492.266
A17: =Suporte!B16 -> Moderado | B17: =Suporte!C16 -> HOTELARIAS | C17: =Suporte!D16 -> 0.1 | D17: =C17*aporte -> 20 | F17: =F16+1 -> 12 | G17: =aporte*12*F17 -> 28800 | H17: =FV(taxa_mensal,F17*12,aporte*-1) -> 68397.072 | I17: =H17-G17 -> 39597.072
A18: =Suporte!B17 -> Agressivo | B18: =Suporte!C17 -> PAPEL | C18: =Suporte!D17 -> 0.5 | D18: =C18*aporte -> 100 | F18: =F17+1 -> 13 | G18: =aporte*12*F18 -> 31200 | H18: =FV(taxa_mensal,F18*12,aporte*-1) -> 80345.734 | I18: =H18-G18 -> 49145.734
... A23: =Suporte!B22 -> Agressivo | B23: =Suporte!C22 -> HOTELARIAS | C23: =Suporte!D22 -> 0.1 | D23: =C23*aporte -> 20 | F23: =F22+1 -> 18 | G23: =aporte*12*F23 -> 43200 | H23: =FV(taxa_mensal,F23*12,aporte*-1) -> 169729.88 | I23: =H23-G23 -> 126529.88
F24: =F23+1 -> 19 | G24: =aporte*12*F24 -> 45600 | H24: =FV(taxa_mensal,F24*12,aporte*-1) -> 195606.45 | I24: =H24-G24 -> 150006.45
F25: =F24+1 -> 20 | G25: =aporte*12*F25 -> 48000 | H25: =FV(taxa_mensal,F25*12,aporte*-1) -> 225039.68 | I25: =H25-G25 -> 177039.68
F26: =F25+1 -> 21 | G26: =aporte*12*F26 -> 50400 | H26: =FV(taxa_mensal,F26*12,aporte*-1) -> 258518.43 | I26: =H26-G26 -> 208118.43
F27: =F26+1 -> 22 | G27: =aporte*12*F27 -> 52800 | H27: =FV(taxa_mensal,F27*12,aporte*-1) -> 296598.74 | I27: =H27-G27 -> 243798.74
F28: =F27+1 -> 23 | G28: =aporte*12*F28 -> 55200 | H28: =FV(taxa_mensal,F28*12,aporte*-1) -> 339913.07 | I28: =H28-G28 -> 284713.07
F29: =F28+1 -> 24 | G29: =aporte*12*F29 -> 57600 | H29: =FV(taxa_mensal,F29*12,aporte*-1) -> 389180.85 | I29: =H29-G29 -> 331580.85
F30: =F29+1 -> 25 | G30: =aporte*12*F30 -> 60000 | H30: =FV(taxa_mensal,F30*12,aporte*-1) -> 445220.33 | I30: =H30-G30 -> 385220.33
F31: =F30+1 -> 26 | G31: =aporte*12*F31 -> 62400 | H31: =FV(taxa_mensal,F31*12,aporte*-1) -> 508962.29 | I31: =H31-G31 -> 446562.29
F32: =F31+1 -> 27 | G32: =aporte*12*F32 -> 64800 | H32: =FV(taxa_mensal,F32*12,aporte*-1) -> 581465.41 | I32: =H32-G32 -> 516665.41
F33: =F32+1 -> 28 | G33: =aporte*12*F33 -> 67200 | H33: =FV(taxa_mensal,F33*12,aporte*-1) -> 663933.87 | I33: =H33-G33 -> 596733.87
F34: =F33+1 -> 29 | G34: =aporte*12*F34 -> 69600 | H34: =FV(taxa_mensal,F34*12,aporte*-1) -> 757737.38 | I34: =H34-G34 -> 688137.38
F35: =F34+1 -> 30 | G35: =aporte*12*F35 -> 72000 | H35: =FV(taxa_mensal,F35*12,aporte*-1) -> 864433.93 | I35: =H35-G35 -> 792433.93
F36: Premissas: aportes no fim de cada mês, taxa mensal constante (Calculos!C18, informada pelo usuário).
